{
  "generated_at": "2026-05-30T09:24:42",
  "spot_slug": "la-jolla",
  "spot_name": "La Jolla",
  "location": "La Jolla, San Diego",
  "region": "California",
  "date": "2026-05-30",
  "numeric_score_0_100": 58,
  "grade": "D",
  "grade_probabilities": {
    "F": 0.02832669655982554,
    "D": 0.5086284559642432,
    "C": 0.3428294511580965,
    "B": 0.12021539631783473,
    "A": 0.0,
    "A+": 0.0
  },
  "raw_grade_probabilities": {
    "F": 0.02832669655982554,
    "D": 0.5086284559642432,
    "C": 0.3428294511580965,
    "B": 0.12021539631783473,
    "A": 0.0,
    "A+": 0.0
  },
  "model_source": "soft_probabilistic",
  "estimated_visibility_range_ft": [
    5,
    9
  ],
  "estimated_visibility_mid_ft": 7.0,
  "raw_expected_vis_ft": 10.09,
  "guardrail_applied": false,
  "confidence": "medium",
  "best_window": "Early morning to late morning before wind builds",
  "risk_factors": [
    "Elevated surf can stir up the shallows."
  ],
  "positive_factors": [
    "Overall swell load is modest.",
    "Wave energy is on the lower side."
  ],
  "explanation": "Conditions score blends swell, wave energy, and wind with the open sandy shore calibration. La Jolla soft probabilistic model \u2014 development data only.  Prospective validation required before public accuracy claims.  See PROSPECTIVE_VALIDATION_PLAN.md.",
  "is_projected": false,
  "projected_from": null,
  "forecast_basis": "Open-Meteo marine components (coherent hourly swell)",
  "report_text": "3:00 PM Update - Grade D\nViz is expected around 5-9 ft. Elevated surf can stir up the shallows.\nBest shot: early morning to late morning before wind builds.\nWaves: 3.7 ft | Wind: 8.9 mph | Water: 66.2\u00b0F | Swell: 2.7 ft @ 4s W",
  "features": {
    "date": "2026-05-30",
    "coherent_swell_source": "hourly_max_height_event",
    "surf_height_mean_ft": 3.74,
    "surf_height_max_ft": 3.74,
    "primary_swell_height_mean_ft": 2.69,
    "primary_swell_height_max_ft": 2.69,
    "primary_swell_period_mean_s": 4.45,
    "primary_swell_period_max_s": 4.45,
    "swell_wave_height_max_ft": 2.69,
    "swell_wave_period_max_s": 4.45,
    "swell_wave_direction_deg": 277,
    "swell_direction_label": "W",
    "wind_wave_height_max_ft": 0.52,
    "wind_wave_period_max_s": 2.0,
    "secondary_swell_height_ft": 1.9,
    "secondary_swell_period_s": 12.3,
    "secondary_swell_direction_deg": 209,
    "secondary_swell_direction_label": "SSW",
    "ml_p1_height_ft": 2.69,
    "ml_p1_period_s": 4.45,
    "ml_p1_direction_deg": 277,
    "ml_p2_height_ft": 1.9,
    "ml_p2_period_s": 12.3,
    "ml_p2_direction_deg": 209,
    "ml_ww_height_ft": 0.52,
    "ml_ww_period_s": 2.0,
    "ml_wave_yesterday_ft": 2.82,
    "ml_wave_2d_ago_ft": 3.36,
    "ml_wave_3d_ago_ft": 4.25,
    "ml_wave_7d_avg_ft": 3.13,
    "rain_target_day_forecast_in": 0.0,
    "rain_prior_3day_in": 0.016,
    "rain_prior_7day_in": 0.016,
    "rain_24h_in": 0.0,
    "ml_rain_3day_in": 0.016,
    "ml_rain_7day_in": 0.016,
    "ml_gust_max_mph": 10.1,
    "ml_sst_f": 66.2,
    "ml_sin_doy": 0.5322,
    "ml_cos_doy": -0.8466,
    "ml_month": 5.0,
    "ml_buoy_ht_ft": 2.69,
    "ml_buoy_per_s": 4.45,
    "ml_buoy_dir_deg": 277,
    "ml_buoy_exp": 0.891,
    "ml_buoy_energy_wtd": 2.87,
    "ml_wind_dir_deg": 310,
    "ml_upwelling_wind": 0.94,
    "ml_chla_log": null,
    "ml_chla_7d_avg": null,
    "ml_pressure_trend": 0.0,
    "ml_sst_anomaly": 2.7,
    "ml_wave_trend": -0.31,
    "ml_wave_accel": -0.54,
    "ml_tide_min_ft": -0.62,
    "ml_tide_range_ft": 6.35,
    "ml_tide_morning_avg": 2.11,
    "wave_height_max_ft": 3.74,
    "wind_speed_mean_mph": 5.7,
    "wind_speed_max_mph": 8.9,
    "wind_gust_max_mph": 10.1,
    "wave_energy_mean_kj": 44.82,
    "wave_energy_max_kj": 44.82,
    "total_swell_height_mean_ft": 2.74,
    "total_swell_height_max_ft": 2.74,
    "swell_power_proxy_mean": 44.82,
    "swell_power_proxy_max": 44.82,
    "short_period_swell_energy": 0.551,
    "long_period_swell_energy": 44.269,
    "mixed_swell_score": 2,
    "wind_wave_churn_proxy": 9.344,
    "wave_energy_wind_interaction": 398.898,
    "water_temp_estimate_f": 66.2,
    "air_temp_max_f": 68.7,
    "air_temp_min_f": 55.2,
    "tide_range_ft": 6.35,
    "wind_chart": [
      {
        "time": "00:00",
        "speed_mph": 4.3
      },
      {
        "time": "01:00",
        "speed_mph": 2.9
      },
      {
        "time": "02:00",
        "speed_mph": 3.5
      },
      {
        "time": "03:00",
        "speed_mph": 4.7
      },
      {
        "time": "04:00",
        "speed_mph": 4.1
      },
      {
        "time": "05:00",
        "speed_mph": 3.3
      },
      {
        "time": "06:00",
        "speed_mph": 3.2
      },
      {
        "time": "07:00",
        "speed_mph": 2.7
      },
      {
        "time": "08:00",
        "speed_mph": 4.2
      },
      {
        "time": "09:00",
        "speed_mph": 5.4
      },
      {
        "time": "10:00",
        "speed_mph": 6.5
      },
      {
        "time": "11:00",
        "speed_mph": 7.9
      },
      {
        "time": "12:00",
        "speed_mph": 8.6
      },
      {
        "time": "13:00",
        "speed_mph": 8.9
      },
      {
        "time": "14:00",
        "speed_mph": 8.6
      },
      {
        "time": "15:00",
        "speed_mph": 8.2
      },
      {
        "time": "16:00",
        "speed_mph": 7.5
      },
      {
        "time": "17:00",
        "speed_mph": 7.5
      },
      {
        "time": "18:00",
        "speed_mph": 6.7
      },
      {
        "time": "19:00",
        "speed_mph": 5.5
      },
      {
        "time": "20:00",
        "speed_mph": 3.6
      },
      {
        "time": "21:00",
        "speed_mph": 3.5
      },
      {
        "time": "22:00",
        "speed_mph": 2.9
      },
      {
        "time": "23:00",
        "speed_mph": 3.2
      }
    ],
    "wave_chart": [
      {
        "time": "00:00",
        "height_ft": 2.8
      },
      {
        "time": "01:00",
        "height_ft": 2.8
      },
      {
        "time": "02:00",
        "height_ft": 2.8
      },
      {
        "time": "03:00",
        "height_ft": 2.9
      },
      {
        "time": "04:00",
        "height_ft": 2.9
      },
      {
        "time": "05:00",
        "height_ft": 3.0
      },
      {
        "time": "06:00",
        "height_ft": 3.0
      },
      {
        "time": "07:00",
        "height_ft": 3.1
      },
      {
        "time": "08:00",
        "height_ft": 3.1
      },
      {
        "time": "09:00",
        "height_ft": 3.2
      },
      {
        "time": "10:00",
        "height_ft": 3.3
      },
      {
        "time": "11:00",
        "height_ft": 3.4
      },
      {
        "time": "12:00",
        "height_ft": 3.5
      },
      {
        "time": "13:00",
        "height_ft": 3.5
      },
      {
        "time": "14:00",
        "height_ft": 3.5
      },
      {
        "time": "15:00",
        "height_ft": 3.5
      },
      {
        "time": "16:00",
        "height_ft": 3.5
      },
      {
        "time": "17:00",
        "height_ft": 3.5
      },
      {
        "time": "18:00",
        "height_ft": 3.5
      },
      {
        "time": "19:00",
        "height_ft": 3.5
      },
      {
        "time": "20:00",
        "height_ft": 3.6
      },
      {
        "time": "21:00",
        "height_ft": 3.7
      },
      {
        "time": "22:00",
        "height_ft": 3.7
      },
      {
        "time": "23:00",
        "height_ft": 3.7
      }
    ],
    "tide_chart": [
      {
        "time": "00:00",
        "height_ft": 2.73
      },
      {
        "time": "01:00",
        "height_ft": 1.38
      },
      {
        "time": "02:00",
        "height_ft": 0.24
      },
      {
        "time": "03:00",
        "height_ft": -0.46
      },
      {
        "time": "04:00",
        "height_ft": -0.62
      },
      {
        "time": "05:00",
        "height_ft": -0.26
      },
      {
        "time": "06:00",
        "height_ft": 0.5
      },
      {
        "time": "07:00",
        "height_ft": 1.44
      },
      {
        "time": "08:00",
        "height_ft": 2.34
      },
      {
        "time": "09:00",
        "height_ft": 2.99
      },
      {
        "time": "10:00",
        "height_ft": 3.29
      },
      {
        "time": "11:00",
        "height_ft": 3.23
      },
      {
        "time": "12:00",
        "height_ft": 2.92
      },
      {
        "time": "13:00",
        "height_ft": 2.52
      },
      {
        "time": "14:00",
        "height_ft": 2.24
      },
      {
        "time": "15:00",
        "height_ft": 2.23
      },
      {
        "time": "16:00",
        "height_ft": 2.56
      },
      {
        "time": "17:00",
        "height_ft": 3.22
      },
      {
        "time": "18:00",
        "height_ft": 4.07
      },
      {
        "time": "19:00",
        "height_ft": 4.91
      },
      {
        "time": "20:00",
        "height_ft": 5.52
      },
      {
        "time": "21:00",
        "height_ft": 5.73
      },
      {
        "time": "22:00",
        "height_ft": 5.42
      },
      {
        "time": "23:00",
        "height_ft": 4.6
      }
    ],
    "source": "open_meteo_marine_coherent",
    "marine_data_filled": false
  },
  "cams": [
    {
      "title": "Scripps Pier Live Visibility",
      "url": "https://coollab.ucsd.edu/pierviz/",
      "embed": null
    }
  ],
  "tide_source": "NOAA La Jolla 9410230 - 2026-05-30",
  "wind_source": "Open-Meteo hourly wind - 2026-05-30",
  "description": "La Jolla dive visibility forecast \u2014 La Jolla Cove, Shores, Canyon, and adjacent kelp forest.  Model trained on La Jolla DivePro reports.  Development model: not validated for public accuracy claims.",
  "habitat": "Kelp forest and sand channels",
  "exposure": "Open sandy shore",
  "calibration_note": "La Jolla soft probabilistic model \u2014 development data only.  Prospective validation required before public accuracy claims.  See PROSPECTIVE_VALIDATION_PLAN.md.",
  "camera_note": "Screenshot refreshes every few minutes from the Scripps Institution of Oceanography pier cam."
}